CHANGELOG.txt
LICENSE.txt
MANIFEST.in
README.txt
setup.py
Basic_files/__init__.py
pynitza.egg-info/PKG-INFO
pynitza.egg-info/SOURCES.txt
pynitza.egg-info/dependency_links.txt
pynitza.egg-info/requires.txt
pynitza.egg-info/top_level.txt