Metadata-Version: 2.1
Name: pynitza
Version: 0.0.1
Summary: Restful api integration package for janitza measuring devices
Home-page: UNKNOWN
Author: Julian Stremel
Author-email: julian-stremel@t-online.de
License: MIT
Keywords: janitza
Platform: UNKNOWN
Classifier: Development Status :: 2 - Pre-Alpha
Classifier: Intended Audience :: Developers
Classifier: License :: OSI Approved :: MIT License
Classifier: Operating System :: Microsoft :: Windows :: Windows 10
Classifier: Programming Language :: Python :: 3
